stickybeak/__init__.py
stickybeak/__version__.py
stickybeak/dj/__init__.py
stickybeak/dj/urls.py
stickybeak/dj/views.py
stickybeak/flask_view.py
stickybeak/handle_requests.py
stickybeak/injector.py
stickybeak/logger.py
stickybeak/sandbox.py
stickybeak/server.py
stickybeak/utils.py
stickybeak/vendored/__init__.py
stickybeak/vendored/inspect.py
stickybeak-0.9.4.dist-info/LICENSE
stickybeak-0.9.4.dist-info/METADATA
stickybeak-0.9.4.dist-info/WHEEL
stickybeak-0.9.4.dist-info/RECORD
