Metadata-Version: 2.1
Name: stickybeak
Version: 0.9.4
Summary: Package that makes e2e tests easy.
Home-page: https://github.com/reloadware/stickybeak
Author: Damian Krystkiewicz
Author-email: damian.krystkiewicz@gmail.com
Requires-Python: >=3.8,<4.0
Classifier: Development Status :: 4 - Beta
Classifier: Intended Audience :: Developers
Classifier: Operating System :: POSIX :: Linux
Classifier: Programming Language :: Python :: 3
Classifier: Programming Language :: Python :: 3.8
Classifier: Programming Language :: Python :: 3.9
Classifier: Programming Language :: Python :: 3.10
Classifier: Programming Language :: Python :: 3.11
Classifier: Programming Language :: Python :: 3.12
Classifier: Programming Language :: Python :: 3 :: Only
Classifier: Programming Language :: Python :: 3.7
Classifier: Programming Language :: Python :: Implementation :: CPython
Requires-Dist: dill
Requires-Dist: jinja2 (>=3.1.4,<4.0.0)
Requires-Dist: pytest (>=8.3.2,<9.0.0)
Requires-Dist: requests
Requires-Dist: typing-extensions
Requires-Dist: virtualenv
